Metadata-Version: 2.0
Name: django-admin-sso2
Version: 2.0.4
Summary: Django SSO solution
Home-page: http://github.com/matthiask/django-admin-sso/
Author: Marc Egli
Author-email: egli@allink.ch
License: BSD License
Platform: OS Independent
Classifier: Development Status :: 5 - Production/Stable
Classifier: Environment :: Web Environment
Classifier: Framework :: Django
Classifier: Intended Audience :: Developers
Classifier: License :: OSI Approved :: BSD License
Classifier: Operating System :: OS Independent
Classifier: Programming Language :: Python
Classifier: Topic :: Internet :: WWW/HTTP :: Dynamic Content
Requires-Dist: Django (>=1.7)
Requires-Dist: oauth2client (>=1.2)
